{
  "gates": [
    {
      "ci_enforced": true,
      "command_or_evidence": "pytest -m \"unit or artifact_public or smoke\" -q",
      "gate_id": "public_smoke_ci",
      "gate_label": "Public smoke CI",
      "remaining_work": "Keep expanding public smoke coverage as new atlas surfaces are added.",
      "scope": "public package install, artifact smoke checks, and root command help",
      "status": "implemented"
    },
    {
      "ci_enforced": true,
      "command_or_evidence": "public smoke tests inspect wheel/package resources",
      "gate_id": "package_content",
      "gate_label": "Package content gate",
      "remaining_work": "Add checksum checks for future larger release assets.",
      "scope": "experiment configs, public rebuild modules, and runner entry points",
      "status": "implemented"
    },
    {
      "ci_enforced": true,
      "command_or_evidence": "public artifact smoke tests scan reader-facing surfaces",
      "gate_id": "public_forbidden_language",
      "gate_label": "Reader-language gate",
      "remaining_work": "Add any newly rejected public phrases to the scanner before release.",
      "scope": "public README, HTML article/supplement/document, atlas, KG, and evidence pages",
      "status": "implemented"
    },
    {
      "ci_enforced": true,
      "command_or_evidence": "public artifact smoke tests and artifact index checks",
      "gate_id": "link_and_schema_smoke",
      "gate_label": "Link and schema smoke gate",
      "remaining_work": "Add browser-level crawl checks for dynamically generated route states.",
      "scope": "local links, indexed public artifacts, KG schema, and manifest coverage",
      "status": "implemented"
    },
    {
      "ci_enforced": true,
      "command_or_evidence": "reproducibility/environment/public_environment_lock.*",
      "gate_id": "environment_lock",
      "gate_label": "Public environment lock",
      "remaining_work": "Add a full experiment container or lockfile before Benchmark v2 execution.",
      "scope": "public smoke-test dependency surface",
      "status": "implemented"
    },
    {
      "ci_enforced": false,
      "command_or_evidence": "skip links, focus-visible styles, captions, canonical URLs, citation metadata, JSON-LD, sitemap, and robots files",
      "gate_id": "accessibility_metadata",
      "gate_label": "Accessibility and academic metadata gate",
      "remaining_work": "Add automated axe/lighthouse-style checks and tagged-PDF validation.",
      "scope": "main public pages and atlas pages",
      "status": "partial"
    },
    {
      "ci_enforced": false,
      "command_or_evidence": "not yet enforced in public CI",
      "gate_id": "lint_type_security",
      "gate_label": "Lint, type, and security gates",
      "remaining_work": "Introduce ruff, mypy/pyright subset, pip-audit, and secret scan gates after public/restricted test split stabilizes.",
      "scope": "Python style, import hygiene, type surface, dependency and secret scanning",
      "status": "planned"
    },
    {
      "ci_enforced": false,
      "command_or_evidence": "monolithic source builders remain tracked as maintenance debt",
      "gate_id": "builder_modularization",
      "gate_label": "Builder modularization gate",
      "remaining_work": "Split builders into DAG tasks with shared schema, path, provenance, and rendering helpers.",
      "scope": "knowledge graph and publication builders",
      "status": "planned"
    },
    {
      "ci_enforced": false,
      "command_or_evidence": "not yet enforced in public CI",
      "gate_id": "schema_migration",
      "gate_label": "Schema migration gate",
      "remaining_work": "Add schema fixtures and migration tests before Benchmark v2 results are generated.",
      "scope": "versioned atlas, KG, evidence, and result-cube schemas",
      "status": "planned"
    }
  ],
  "generated_at_utc": "2026-07-15T03:02:40.892531+00:00",
  "schema": "regression_cp_public_maintenance_gate_matrix_v1",
  "summary": {
    "ci_enforced_gate_count": 5,
    "gate_count": 9,
    "implemented_gate_count": 5,
    "overall_status": "maintenance_gates_defined_modularization_pending",
    "partial_gate_count": 1,
    "planned_gate_count": 3
  }
}
